jupyterlab_reset_fixer/__init__.py
jupyterlab_reset_fixer/_version.py
jupyterlab_reset_fixer/labextension/package.json
jupyterlab_reset_fixer/labextension/static/568.fd4da311aae3fad363c7.js
jupyterlab_reset_fixer/labextension/static/747.7e3b3d1a2cce1a821201.js
jupyterlab_reset_fixer/labextension/static/remoteEntry.aa7f95daf370d8bfb919.js
jupyterlab_reset_fixer/labextension/static/style.js
jupyterlab_reset_fixer/labextension/static/third-party-licenses.json
jupyterlab_reset_fixer-1.0.0.data/data/share/jupyter/labextensions/jupyterlab-reset-fixer/install.json
jupyterlab_reset_fixer-1.0.0.data/data/share/jupyter/labextensions/jupyterlab-reset-fixer/package.json
jupyterlab_reset_fixer-1.0.0.data/data/share/jupyter/labextensions/jupyterlab-reset-fixer/static/568.fd4da311aae3fad363c7.js
jupyterlab_reset_fixer-1.0.0.data/data/share/jupyter/labextensions/jupyterlab-reset-fixer/static/747.7e3b3d1a2cce1a821201.js
jupyterlab_reset_fixer-1.0.0.data/data/share/jupyter/labextensions/jupyterlab-reset-fixer/static/remoteEntry.aa7f95daf370d8bfb919.js
jupyterlab_reset_fixer-1.0.0.data/data/share/jupyter/labextensions/jupyterlab-reset-fixer/static/style.js
jupyterlab_reset_fixer-1.0.0.data/data/share/jupyter/labextensions/jupyterlab-reset-fixer/static/third-party-licenses.json
jupyterlab_reset_fixer-1.0.0.dist-info/LICENSE
jupyterlab_reset_fixer-1.0.0.dist-info/METADATA
jupyterlab_reset_fixer-1.0.0.dist-info/WHEEL
jupyterlab_reset_fixer-1.0.0.dist-info/top_level.txt
jupyterlab_reset_fixer-1.0.0.dist-info/RECORD
